README.rst
setup.py
uplook/__init__.py
uplook/errors.py
uplook.egg-info/PKG-INFO
uplook.egg-info/SOURCES.txt
uplook.egg-info/dependency_links.txt
uplook.egg-info/namespace_packages.txt
uplook.egg-info/not-zip-safe
uplook.egg-info/requires.txt
uplook.egg-info/top_level.txt